[
	{
		"name": "Maglein",
		"leaderName": "Zinovy Maksimilian",
		"adjective": ["Maglian"],
		"preferredVictoryType": "Diplomatic",
		
		"startIntroPart1": "Your goal is to build the UN Station to win. Do anything you want that is necessary to achieve your utmost goal of this game",
		
		"declaringWar": "'We stand united...ready and prepared to go to war in order to protect our citizens and uphold the values that built our great nation.'",
		"attacked": "'We will prevail and emerge victorious.'",
		"defeated": "'War will be waged until our sovereignty is recognized and our territory is rightfully claimed.'",
		"introduction": "'Oh, nice to meet you. Just passing through.'",
		
		"neutralHello": "How are you doing?",
		"neutralLetsHearIt": ["Go on.","What do you say?","You may begin."],
		"neutralNo": ["We absolutely refuse.","No!","I refuse."],
		"neutralYes": ["Very good.","Of course, yes.","That is very good."],

		"hateHello": "What do you want now?",
		"hateLetsHearIt": ["Speak!","What do you say?","Go on."],
		"hateNo": ["That is not possible!","We are not agreeing to that!","I beg your pardon?"],
		"hateYes": ["That is fine.","That is good enough.","Very well..."],
		
		"afterPeace": "My people stand with me in this struggle and will not rest until victory is ours.",
		"tradeRequest": "'What do you say? Good deal, ain't it?'",

		"outerColor": [26,39,88],
		"innerColor": [255,255,255],
		"unique": "MANIFEST_DESTINY",
		"cities": ["Roskov", "Artyom", "Gropham", "Rozkha", "Sukharenov", "Ahmedikov", "Yazidunik", "Raveduvich"]
	},
	{
		"name": "Yodrea",
		"leaderName": "Tarō Noriaki",
		"adjective": ["Yodranese"],
		"preferredVictoryType": "Scientific",
		
		"declaringWar": "'Stand with me in this fight against the enemy.'",
		"attacked": "'Let us rise and ready ourselves for a battle that we must win, for our futures depend on the outcome'",
		"defeated": "'We resign ourselves to the mercy of the enemy and submit to their terms.'",
		"introduction": "Oh, hello. Don't attack me. I'm friendly and I am just passing through...",
		
		"neutralHello": "How are you doing?",
		"neutralLetsHearIt": "Sure.",
		"neutralNo": "No.",
		"neutralYes": ["Very well."],

		"hateHello": "What do you want now?",
		"hateLetsHearIt": ["Speak!","What do you say?","Go on."],
		"hateNo": ["That is not possible!","We are not agreeing to that!","I beg your pardon?"],
		"hateYes": ["That is fine.","That is good enough.","Very well..."],
		
		"afterPeace": "Very well, all that fighting was getting boring anyway.",
		"tradeRequest": "We bestow you the honor of this trade offer.",

		"outerColor": [49,49,49],
		"innerColor": [11,107,60],
		"unique": "MANIFEST_DESTINY",
		"cities": [ "Shōhei", "Yoshimitsu", "Tatsuya", "Katsurou", "Keita", "Akio", "Katsu", "Jūrō", "Noriaki", "Masao", "Masaharu", "Yamato", "Kazuhiko", "Gorou", "Nobuyuki", "Isamu", "Fumio", "Fumiko", "Mitaka", "Hayakawa", "Satoshi", "Yūta", "Shinji", "Shinichi" ]
	},
	{
		"name": "Cynoc",
		"leaderName": "PJ",
		"adjective": ["Cynese"],
		"preferredVictoryType": "Scientific",
		
		"startIntroPart1": "Greetings, Traveller.",
		"startIntroPart2": "Well, it looks like we found another. Hello, we come in peace.",
		
		"declaringWar": "Please don't resist. Make this easy for us. Nothing personal.",
		"attacked": "Are you sure you want to do this?",
		"defeated": "Goddammit... We were too... weak...",
		"introduction": "Don't bother, please.",
		
		"neutralHello": "Greetings!",
		"neutralLetsHearIt": ["Please continue.","Oh?","Let us hear your thoughts."],
		"neutralNo": ["No.","I'm afraid I would have to disagree.","Simply, I cannot agree with you."],
		"neutralYes": ["Yes.","Of course, yes.","That is very good."],

		"hateHello": "Do you need anything?",
		"hateLetsHearIt": ["I'll hear you out.","Don't expect me to agree with you so easily, but continue.","Go on."],
		"hateNo": ["No.","Hell no.","I beg your pardon?"],
		"hateYes": ["Acceptable.","Good enough.","You'll have to do better than that, but I'll try and give you a chance."],
		
		"afterPeace": "Thank you, I'm glad you have ceased.",
		"tradeRequest": "We would like to trade. Would this barter be acceptable?",

		"outerColor": [0,107,107],
		"innerColor": [255,212,0],
		"unique": "MANIFEST_DESTINY",
		"cities": ["rename paul"]
	},
	{
		"name": "Rocros",
		"leaderName": "Noah Meinhard",
		"adjective": ["Rocroation"],
		"preferredVictoryType": "Domination",
		
	//	"startIntroPart1": "Welcome, my friend.",
	//	"startIntroPart2": "Remember, no witnesses. I mean, hello, we come in peace!",
		
		"declaringWar": " 'We will vanquish our enemies and show them the true meaning of power.'",
		"attacked": "'Enough is enough!'",
		"defeated": "'We will not rest until we have achieved total victory!'",
		"introduction": "'Just a friendly individual passing by...'",
		
		"neutralHello": "How are you doing?",
		"neutralLetsHearIt": ["Go on.","What do you say?","You may begin."],
		"neutralNo": ["We absolutely refuse.","No!","I refuse."],
		"neutralYes": ["Very good.","Of course, yes.","That is very good."],

		"hateHello": "What do you want now?",
		"hateLetsHearIt": ["Speak!","What do you say?","Go on."],
		"hateNo": ["That is not possible!","We are not agreeing to that!","I beg your pardon?"],
		"hateYes": ["That is fine.","That is good enough.","Very well..."],
		
		"afterPeace": "'We will fight until the last breath! We swore that we will turn things around in the future!'",
		"tradeRequest": "Got something that might interest ya!",

		"outerColor": [26,88,26],
		"innerColor": [255,255,255],
		"unique": "MANIFEST_DESTINY",
		"cities": ["Bernadette", "Hildegard", "Regula", "Dagmar", "Elise", "Helga", "Svenja", "Walpurga", "Salome", "Ortrun", "Marianne", "Marcella", "Liese", "Konstanze", "Magdalena", "Liesl", "Selma", "Dietlinde", "Margit", "Ribelio"]
	},
	{
		"name": "Achesh",
		"leaderName": "Thamir Husayn Salih Arif",
		"adjective": ["Achesian"],
		"preferredVictoryType": "Time",

		"startIntroPart1": "Your goal is to survive until 900 turns to win. Do anything you want that is necessary to achieve your utmost goal of this game",
		
		"declaringWar": "'We must act with determination and resolve to safeguard our interests and protect our people.'",
		"attacked": "'My people are ready, and I am determined to see this fight through until the end. '",
		"defeated": "'For now, our cause is lost, and we must resign ourselves to our fate.'",
		"introduction": "Leave me alone and I'll let you be. I'm just passing through..",
		
		"neutralHello": "How are you doing?",
		"neutralLetsHearIt": ["Go on.","What do you say?","You may begin."],
		"neutralNo": ["We absolutely refuse.","No!","I refuse."],
		"neutralYes": ["Very good.","Of course, yes.","That is very good."],

		"hateHello": "What do you want now?",
		"hateLetsHearIt": ["Speak!","What do you say?","Go on."],
		"hateNo": ["That is not possible!","We are not agreeing to that!","I beg your pardon?"],
		"hateYes": ["That is fine.","That is good enough.","Very well..."],
		
		"afterPeace": "'Let us look forward to better days.'",
		"tradeRequest": "We bestow you the honor of this trade offer.",

		"outerColor": [255,0,0],
		"innerColor": [255,255,255],
		"cities": ["Alekos","Faizel", "Burhan", "Ebrahim", "Saeed", "Husam", "I'timad", "Jinan", "Najeeb", "Ismaeel", "Zayd", "Midhat", "Younes", "Shams al-Din Sa'id", "Mahmoud","Miraj", "Farag", "Abduh", "Haider", "'Ammar", "Jaouad", "Murtada", "Bassem", "Amna", "Fakhriyya", "Basira", "Masoud", "Ramlah", "Zoubida", "Safaa", "Bahija", "Sabri", "Mubira", "Zoubida", "Burhanuddin" ]
	},
	{
		"name": "Stington",
		"leaderName": "Myrna Aoibhe",
		"adjective": ["English"],
		"preferredVictoryType": "Cultural",

				"startIntroPart1": "Your goal is to max out five policies to win. Do anything you want that is necessary to achieve your utmost goal of this game",
		
		"declaringWar": "'My people, stand with me, and together we will prevail!'",
		"attacked": "'I have heard the call, and I am prepared to fight.'",
		"defeated": "'Our honor has been tarnished, and our pride remains battered'",
		"introduction": "Just passing by!",
		"neutralHello": "Greetings",
		"neutralLetsHearIt": "What is on your mind?",
		"neutralNo": "Absolutely no.",
		"neutralYes": ["Very good.","Of course, yes.","That is very good."],

		"hateHello": "What do you want now?",
		"hateLetsHearIt": ["Speak!","What do you say?","Go on."],
		"hateNo": ["That is not possible!","We are not agreeing to that!","I beg your pardon?"],
		"hateYes": ["That is fine.","That is good enough.","Very well..."],
		
		"afterPeace": "' I now surrender myself to the enemy, in the hope that my surrender will prevent further bloodshed and bring peace to our lands.'",
		"tradeRequest": "What do you think?",

		"outerColor": [42,173,175],
		"innerColor": [255,255,255],
		"cities": ["Aroldo","Patricio", "Murdo", "Marian", "Jahangir", "Secundinus", "Perseus", "Percival", "Hermógenes", "Kaneonuskatew", "Asar", "Dominik", "Boshustan", "Eskya", "Hildimar","Prometheus", "Evgeniy", "Romulus", "Volodimeru", "Hermolaos", "Huckleberry", "Bartoloměj", "Sindri", "Prual Prington", "Pyrrhos", "Chobin", "Deskiaqua", "Chikumbutso", "Eutimio", "Bahram", "Fesmeiria", "Vawhines", "Ansoald", "Nicolás", "Alkaios" ]
	},
	{
		"name": "Lino",
		"leaderName": "António Hanna",
		"adjective": ["Linoise"],
		"preferredVictoryType": "Diplomatic",

				"startIntroPart1": "Your goal is to build the UN Station to win. Do anything you want that is necessary to achieve your utmost goal of this game",
		
		"declaringWar": "Together, we shall overthrow the evil rulers and reclaim our freedom.",
		"attacked": " Let us stand strong and fight back, and let our leaders know that we shall not waver in the face of adversity.",
		"defeated": "It wasn't supposed to end this way.",
		"introduction": "We hope to establish friendly relations with you, and work together for a better future.",
		"neutralHello": "Greetings",
		"neutralLetsHearIt": "What is on your mind?",
		"neutralNo": "Absolutely no.",
		"neutralYes": ["Very good.","Of course, yes.","That is very good."],

		"hateHello": "What do you want now?",
		"hateLetsHearIt": ["Speak!","What do you say?","Go on."],
		"hateNo": ["That is not possible!","We are not agreeing to that!","I beg your pardon?"],
		"hateYes": ["That is fine.","That is good enough.","Very well..."],
		
		"afterPeace": "Very well, all that fighting was getting boring anyway.",
		"tradeRequest": "What do you think?",

		"outerColor": [19,19,19],
		"innerColor": [255,0,0],
		"cities": ["Praskoviya","Vasily", "Lilya", "Demid", "Anastasia", "Anzhela", "Semion", "Yekaterina", "Makar", "Wassily", "Pasha", "Lavrenti", "Anatoly", "Yana", "Daria","Lara", "Nadezhda", "Klavdiya", "Innokenti", "Genya", "Yevgeniy", "Rolan", "Venyamin", "Artemi", "Nikodim", "Evgeniy", "Evgenia", "Ksenia", "Inessa", "Snezhana", "Avgust", "Violetta", "Sergej", "Renat", "Yeva" ]
	},
	{
		"name": "Pustraustein",
		"leaderName": "Mavuto Hammu-Rapi",
		"adjective": ["Pustrausteinese"],
		"preferredVictoryType": "Cultural",

		"startIntroPart1": "Your goal is to max out five policies to win. Do anything you want that is necessary to achieve your utmost goal of this game",
		
		"declaringWar": "Together, we shall overthrow the evil rulers and reclaim our freedom.",
		"attacked": " Let us stand strong and fight back, and let our leaders know that we shall not waver in the face of adversity.",
		"defeated": "It wasn't supposed to end this way.",
		"introduction": "We hope to establish friendly relations with you, and work together for a better future.",
		"neutralHello": "Greetings",
		"neutralLetsHearIt": "What is on your mind?",
		"neutralNo": "Absolutely no.",
		"neutralYes": ["Very good.","Of course, yes.","That is very good."],

		"hateHello": "What do you want now?",
		"hateLetsHearIt": ["Speak!","What do you say?","Go on."],
		"hateNo": ["That is not possible!","We are not agreeing to that!","I beg your pardon?"],
		"hateYes": ["That is fine.","That is good enough.","Very well..."],
		
		"afterPeace": "Very well, all that fighting was getting boring anyway.",
		"tradeRequest": "What do you think?",

		"outerColor": [255,186,10],
		"innerColor": [10,105,255], //Dominik replace
		"cities": ["Sabahattin","Samo", "Barnaba", "Sanjeev", "Basileios", "Napoleone", "Daniyal", "Hauke", "Gottlieb", "Gotthold", "Reinhardt", "Pierrette", "Garbi", "Vladislav", "Prasad","Camillus", "Michaela", "Heidrun", "Enkhtuya", "Nevena", "Maïwenn", "Adile", "Childeric", "Hildur", "Kallippos", "Yechezkel", "Rolland", "Petra", "Samuela", "Puneet", "Georgene", "Brennus", "Abessalom", "Teunis", "Iusta" ]
	},
	{
		"name": "Cloel Drela",
		"leaderName": "Barabal Findlay",
		"adjective": ["Marinese"],
		"preferredVictoryType": "Domination",

		"startIntroPart1": "Your goal is capture ALL capitals. Do anything you want that is necessary to achieve your utmost goal of this game",
		
		"declaringWar": "Together, we shall overthrow the evil rulers and reclaim our freedom.",
		"attacked": " Let us stand strong and fight back, and let our leaders know that we shall not waver in the face of adversity.",
		"defeated": "It wasn't supposed to end this way.",
		"introduction": "We hope to establish friendly relations with you, and work together for a better future.",
		"neutralHello": "Greetings",
		"neutralLetsHearIt": "What is on your mind?",
		"neutralNo": "Absolutely no.",
		"neutralYes": ["Very good.","Of course, yes.","That is very good."],

		"hateHello": "What do you want now?",
		"hateLetsHearIt": ["Speak!","What do you say?","Go on."],
		"hateNo": ["That is not possible!","We are not agreeing to that!","I beg your pardon?"],
		"hateYes": ["That is fine.","That is good enough.","Very well..."],
		
		"afterPeace": "Very well, all that fighting was getting boring anyway.",
		"tradeRequest": "What do you think?",

		"outerColor": [255,255,255],
		"innerColor": [10,105,255], //Dominik replace
		"cities": ["Tòmas","Frangag", "Dòmhnall", "Neilina", "Tòmas", "Findlay", "Eachann", "Sìne", "Hamish", "Maoilios", "Malcolm", "Moyra", "Ruaridh", "Artair", "Wallace","Raghnaid", "Seòras", "Elspet", "Kenneth", "Moray", "Caitrìona", "Ronald", "Aonghas", "Ciorstaidh", "Maisie", "Scot", "Keith", "Farquhar", "Seonag", "Heckie", "Scot", "Alan", "Aulay", "Muireall", "Naomhán" ]
	},
	{
		"name": "Oclein",
		"leaderName": "Domenic Cammie",
		"adjective": ["Cleinese"],
		"preferredVictoryType": "Time",

		"startIntroPart1": "Your goal is to survive until 900 turns to win. Do anything you want that is necessary to achieve your utmost goal of this game",
		
		"declaringWar": "Together, we shall overthrow the evil rulers and reclaim our freedom.",
		"attacked": " Let us stand strong and fight back, and let our leaders know that we shall not waver in the face of adversity.",
		"defeated": "It wasn't supposed to end this way.",
		"introduction": "We hope to establish friendly relations with you, and work together for a better future.",
		"neutralHello": "Greetings",
		"neutralLetsHearIt": "What is on your mind?",
		"neutralNo": "Absolutely no.",
		"neutralYes": ["Very good.","Of course, yes.","That is very good."],

		"hateHello": "What do you want now?",
		"hateLetsHearIt": ["Speak!","What do you say?","Go on."],
		"hateNo": ["That is not possible!","We are not agreeing to that!","I beg your pardon?"],
		"hateYes": ["That is fine.","That is good enough.","Very well..."],
		
		"afterPeace": "Very well, all that fighting was getting boring anyway.",
		"tradeRequest": "What do you think?",

		"outerColor": [255,255,255],
		"innerColor": [255,186,10], //Dominik replace
		"cities": ["Caelan","Claudia", "Domenic", "Cammie", "Darcie", "Terance", "Teddy", "Quinten", "Nelly", "Winfield", "Nell", "Melanie", "Ella", "Geralyn", "Elenora","Vonda", "Wynona", "Alexander", "Taryn", "Houston", "Chrystal", "Rowley", "Frankie", "Randi", "Marnie", "Emmie", "Zachery", "Gwenda", "Stafford", "Macauley", "Magdalen", "Denton", "Kristin", "Grover", "Phyliss" ]
		
	},
	{
		"name": "Creyla",
		"leaderName": "Velda Nelle",
		"adjective": ["Creyla"],
		"preferredVictoryType": "Diplomatic",

		"startIntroPart1": "Your goal is to build the UN station to win. Do anything you want that is necessary to achieve your utmost goal of this game",
		
		"declaringWar": "Together, we shall overthrow the evil rulers and reclaim our freedom.",
		"attacked": " Let us stand strong and fight back, and let our leaders know that we shall not waver in the face of adversity.",
		"defeated": "It wasn't supposed to end this way.",
		"introduction": "We hope to establish friendly relations with you, and work together for a better future.",
		"neutralHello": "Greetings",
		"neutralLetsHearIt": "What is on your mind?",
		"neutralNo": "Absolutely no.",
		"neutralYes": ["Very good.","Of course, yes.","That is very good."],

		"hateHello": "What do you want now?",
		"hateLetsHearIt": ["Speak!","What do you say?","Go on."],
		"hateNo": ["That is not possible!","We are not agreeing to that!","I beg your pardon?"],
		"hateYes": ["That is fine.","That is good enough.","Very well..."],
		
		"afterPeace": "Very well, all that fighting was getting boring anyway.",
		"tradeRequest": "What do you think?",

		"outerColor": [55,66,132],
		"innerColor": [181,181,181], //Dominik replace
		"cities": ["Jewell","Wendell", "Dorian", "Willie", "Posy", "Roxana", "Avis", "Kermit", "Cherry", "Rose", "Trista", "Zandra", "Cassandra", "Daniela", "Bella","Madonna", "Laraine", "Rhodes", "Harding", "Lorin", "Curtis", "Elizabethe", "Diane", "Freda", "Rudeous", "Lucille", "Alease", "Spencer", "Linette", "Brooke", "Myra", "Nathaniel", "Brion", "Woodrow", "Roscoe" ]
	},
	{
		"name": "Freir Thya",
		"leaderName": "Velda Nelle",
		"adjective": ["Creyla"],
		"preferredVictoryType": "Scientific",

		"startIntroPart1": "Your goal is to build a spaceship to win. Do anything you want that is necessary to achieve your utmost goal of this game",
		
		"declaringWar": "Together, we shall overthrow the evil rulers and reclaim our freedom.",
		"attacked": " Let us stand strong and fight back, and let our leaders know that we shall not waver in the face of adversity.",
		"defeated": "It wasn't supposed to end this way.",
		"introduction": "We hope to establish friendly relations with you, and work together for a better future.",
		"neutralHello": "Greetings",
		"neutralLetsHearIt": "What is on your mind?",
		"neutralNo": "Absolutely no.",
		"neutralYes": ["Very good.","Of course, yes.","That is very good."],

		"hateHello": "What do you want now?",
		"hateLetsHearIt": ["Speak!","What do you say?","Go on."],
		"hateNo": ["That is not possible!","We are not agreeing to that!","I beg your pardon?"],
		"hateYes": ["That is fine.","That is good enough.","Very well..."],
		
		"afterPeace": "Very well, all that fighting was getting boring anyway.",
		"tradeRequest": "What do you think?",

		"outerColor": [60,94,31],
		"innerColor": [255,255,255], //Dominik replace
		"cities": ["Thornton","Eden", "Oakley", "Jasmine", "Averill", "Abigale", "Kirrily", "Ralphie", "Joetta", "Kiley", "Aaron", "Jaxson", "Gale", "Axson", "Averuy","Turuntu", "Madegas", "Madegaz", "Harding", "Bentleye", "Fultton", "Aeretha", "Houlden", "Brynlee", "Flossie", "Emely", "Danita", "Brande", "Gemma", "Britannia", "Kyro", "Mekaulay", "Elise", "Nevaeh", "Remev" ]
	}
	
]
